iteraa/CHANGELOG.md
iteraa/__init__.py
iteraa/constants.py
iteraa/datasets.py
iteraa/iaa.py
iteraa/piaa.py
iteraa/plot.py
iteraa/runAA.py
iteraa/utils.py
iteraa-0.2.0.dist-info/LICENSE
iteraa-0.2.0.dist-info/METADATA
iteraa-0.2.0.dist-info/WHEEL
iteraa-0.2.0.dist-info/RECORD
