Metadata-Version: 2.1
Name: iteraa
Version: 0.2.0
Summary: A package to conduct accelerated archetypal analysis with an iterative approach.
License: MIT
Author: Jonathan Yik Chang Ting
Requires-Python: >=3.11,<4.0
Classifier: License :: OSI Approved :: MIT License
Classifier: Programming Language :: Python :: 3
Classifier: Programming Language :: Python :: 3.11
Requires-Dist: matplotlib (>=3.9.1,<4.0.0)
Requires-Dist: natsort (>=8.4.0,<9.0.0)
Requires-Dist: numpy (<2.0.0)
Requires-Dist: pandas (>=2.2.2,<3.0.0)
Requires-Dist: scikit-learn (>=1.5.1,<2.0.0)
Requires-Dist: scipy (>=1.14.0,<2.0.0) ; python_version >= "3.10" and python_version < "4.0"
Requires-Dist: seaborn (>=0.13.2,<0.14.0)
